{
	"completely_empty": false,
	"image": {
		"height": 1280,
		"scale": 0.57109375,
		"width": 960
	},
	"mark": [
		{
			"class_idx": 6,
			"name": "Libresse",
			"points": [
				{
					"int_x": 795,
					"int_y": 0,
					"x": 0.828421875,
					"y": 0.0
				},
				{
					"int_x": 837,
					"int_y": 0,
					"x": 0.8717031249999999,
					"y": 0.0
				},
				{
					"int_x": 837,
					"int_y": 38,
					"x": 0.8717031249999999,
					"y": 0.030015625
				},
				{
					"int_x": 795,
					"int_y": 38,
					"x": 0.828421875,
					"y": 0.030015625
				}
			],
			"rect": {
				"h": 0.030015625,
				"int_h": 39,
				"int_w": 43,
				"int_x": 795,
				"int_y": 0,
				"w": 0.04328124999999994,
				"x": 0.828421875,
				"y": 0.0
			}
		},
		{
			"class_idx": 1,
			"name": "Bella",
			"points": [
				{
					"int_x": 240,
					"int_y": 24,
					"x": 0.250015625,
					"y": 0.018578125
				},
				{
					"int_x": 289,
					"int_y": 24,
					"x": 0.30121354166666664,
					"y": 0.018578125
				},
				{
					"int_x": 289,
					"int_y": 131,
					"x": 0.30121354166666664,
					"y": 0.10240625
				},
				{
					"int_x": 240,
					"int_y": 131,
					"x": 0.250015625,
					"y": 0.10240625
				}
			],
			"rect": {
				"h": 0.083828125,
				"int_h": 108,
				"int_w": 50,
				"int_x": 240,
				"int_y": 24,
				"w": 0.05119791666666662,
				"x": 0.250015625,
				"y": 0.018578125
			}
		},
		{
			"class_idx": 1,
			"name": "Bella",
			"points": [
				{
					"int_x": 302,
					"int_y": 70,
					"x": 0.3147810218978102,
					"y": 0.05471956224350205
				},
				{
					"int_x": 335,
					"int_y": 70,
					"x": 0.3494525547445255,
					"y": 0.05471956224350205
				},
				{
					"int_x": 335,
					"int_y": 130,
					"x": 0.3494525547445255,
					"y": 0.1012311901504788
				},
				{
					"int_x": 302,
					"int_y": 130,
					"x": 0.3147810218978102,
					"y": 0.1012311901504788
				}
			],
			"rect": {
				"h": 0.046511627906976744,
				"int_h": 61,
				"int_w": 34,
				"int_x": 302,
				"int_y": 70,
				"w": 0.034671532846715314,
				"x": 0.3147810218978102,
				"y": 0.05471956224350205
			}
		},
		{
			"class_idx": 1,
			"name": "Bella",
			"points": [
				{
					"int_x": 334,
					"int_y": 20,
					"x": 0.34811458333333334,
					"y": 0.015605468749999997
				},
				{
					"int_x": 384,
					"int_y": 20,
					"x": 0.40028125000000003,
					"y": 0.015605468749999997
				},
				{
					"int_x": 384,
					"int_y": 125,
					"x": 0.40028125000000003,
					"y": 0.09726953124999999
				},
				{
					"int_x": 334,
					"int_y": 125,
					"x": 0.34811458333333334,
					"y": 0.09726953124999999
				}
			],
			"rect": {
				"h": 0.0816640625,
				"int_h": 106,
				"int_w": 51,
				"int_x": 334,
				"int_y": 20,
				"w": 0.052166666666666694,
				"x": 0.34811458333333334,
				"y": 0.015605468749999997
			}
		},
		{
			"class_idx": 1,
			"name": "Bella",
			"points": [
				{
					"int_x": 385,
					"int_y": 12,
					"x": 0.401390625,
					"y": 0.009054687499999999
				},
				{
					"int_x": 437,
					"int_y": 12,
					"x": 0.45496354166666664,
					"y": 0.009054687499999999
				},
				{
					"int_x": 437,
					"int_y": 121,
					"x": 0.45496354166666664,
					"y": 0.0946171875
				},
				{
					"int_x": 385,
					"int_y": 121,
					"x": 0.401390625,
					"y": 0.0946171875
				}
			],
			"rect": {
				"h": 0.08556250000000001,
				"int_h": 110,
				"int_w": 53,
				"int_x": 385,
				"int_y": 12,
				"w": 0.05357291666666664,
				"x": 0.401390625,
				"y": 0.009054687499999999
			}
		},
		{
			"class_idx": 1,
			"name": "Bella",
			"points": [
				{
					"int_x": 442,
					"int_y": 21,
					"x": 0.46058333333333334,
					"y": 0.016570312500000003
				},
				{
					"int_x": 488,
					"int_y": 21,
					"x": 0.50825,
					"y": 0.016570312500000003
				},
				{
					"int_x": 488,
					"int_y": 134,
					"x": 0.50825,
					"y": 0.1049140625
				},
				{
					"int_x": 442,
					"int_y": 134,
					"x": 0.46058333333333334,
					"y": 0.1049140625
				}
			],
			"rect": {
				"h": 0.08834375,
				"int_h": 114,
				"int_w": 47,
				"int_x": 442,
				"int_y": 21,
				"w": 0.047666666666666635,
				"x": 0.46058333333333334,
				"y": 0.016570312500000003
			}
		},
		{
			"class_idx": 1,
			"name": "Bella",
			"points": [
				{
					"int_x": 489,
					"int_y": 16,
					"x": 0.5096770833333334,
					"y": 0.012804687499999995
				},
				{
					"int_x": 534,
					"int_y": 16,
					"x": 0.5560312500000001,
					"y": 0.012804687499999995
				},
				{
					"int_x": 534,
					"int_y": 131,
					"x": 0.5560312500000001,
					"y": 0.10197656249999999
				},
				{
					"int_x": 489,
					"int_y": 131,
					"x": 0.5096770833333334,
					"y": 0.10197656249999999
				}
			],
			"rect": {
				"h": 0.089171875,
				"int_h": 116,
				"int_w": 46,
				"int_x": 489,
				"int_y": 16,
				"w": 0.046354166666666696,
				"x": 0.5096770833333334,
				"y": 0.012804687499999995
			}
		},
		{
			"class_idx": 1,
			"name": "Bella",
			"points": [
				{
					"int_x": 534,
					"int_y": 32,
					"x": 0.55609375,
					"y": 0.02525
				},
				{
					"int_x": 621,
					"int_y": 32,
					"x": 0.6468645833333333,
					"y": 0.02525
				},
				{
					"int_x": 621,
					"int_y": 142,
					"x": 0.6468645833333333,
					"y": 0.11081250000000001
				},
				{
					"int_x": 534,
					"int_y": 142,
					"x": 0.55609375,
					"y": 0.11081250000000001
				}
			],
			"rect": {
				"h": 0.08556250000000001,
				"int_h": 111,
				"int_w": 88,
				"int_x": 534,
				"int_y": 32,
				"w": 0.09077083333333325,
				"x": 0.55609375,
				"y": 0.02525
			}
		},
		{
			"class_idx": 6,
			"name": "Libresse",
			"points": [
				{
					"int_x": 678,
					"int_y": 33,
					"x": 0.7062604166666666,
					"y": 0.025777343749999987
				},
				{
					"int_x": 787,
					"int_y": 33,
					"x": 0.81984375,
					"y": 0.025777343749999987
				},
				{
					"int_x": 787,
					"int_y": 205,
					"x": 0.81984375,
					"y": 0.16053515625
				},
				{
					"int_x": 678,
					"int_y": 205,
					"x": 0.7062604166666666,
					"y": 0.16053515625
				}
			],
			"rect": {
				"h": 0.13475781250000002,
				"int_h": 173,
				"int_w": 110,
				"int_x": 678,
				"int_y": 33,
				"w": 0.11358333333333337,
				"x": 0.7062604166666666,
				"y": 0.025777343749999987
			}
		},
		{
			"class_idx": 1,
			"name": "Bella",
			"points": [
				{
					"int_x": 239,
					"int_y": 150,
					"x": 0.2485885416666667,
					"y": 0.11684375
				},
				{
					"int_x": 286,
					"int_y": 150,
					"x": 0.29822395833333337,
					"y": 0.11684375
				},
				{
					"int_x": 286,
					"int_y": 254,
					"x": 0.29822395833333337,
					"y": 0.19859374999999999
				},
				{
					"int_x": 239,
					"int_y": 254,
					"x": 0.2485885416666667,
					"y": 0.19859374999999999
				}
			],
			"rect": {
				"h": 0.08174999999999999,
				"int_h": 105,
				"int_w": 48,
				"int_x": 239,
				"int_y": 150,
				"w": 0.04963541666666668,
				"x": 0.2485885416666667,
				"y": 0.11684375
			}
		},
		{
			"class_idx": 1,
			"name": "Bella",
			"points": [
				{
					"int_x": 292,
					"int_y": 143,
					"x": 0.30393229166666663,
					"y": 0.11196484375000001
				},
				{
					"int_x": 341,
					"int_y": 143,
					"x": 0.35519270833333333,
					"y": 0.11196484375000001
				},
				{
					"int_x": 341,
					"int_y": 241,
					"x": 0.35519270833333333,
					"y": 0.18837890625
				},
				{
					"int_x": 292,
					"int_y": 241,
					"x": 0.30393229166666663,
					"y": 0.18837890625
				}
			],
			"rect": {
				"h": 0.07641406249999999,
				"int_h": 99,
				"int_w": 50,
				"int_x": 292,
				"int_y": 143,
				"w": 0.0512604166666667,
				"x": 0.30393229166666663,
				"y": 0.11196484375000001
			}
		},
		{
			"class_idx": 1,
			"name": "Bella",
			"points": [
				{
					"int_x": 378,
					"int_y": 141,
					"x": 0.39408333333333334,
					"y": 0.11001562499999998
				},
				{
					"int_x": 427,
					"int_y": 141,
					"x": 0.4446458333333333,
					"y": 0.11001562499999998
				},
				{
					"int_x": 427,
					"int_y": 255,
					"x": 0.4446458333333333,
					"y": 0.199234375
				},
				{
					"int_x": 378,
					"int_y": 255,
					"x": 0.39408333333333334,
					"y": 0.199234375
				}
			],
			"rect": {
				"h": 0.08921875000000001,
				"int_h": 115,
				"int_w": 50,
				"int_x": 378,
				"int_y": 141,
				"w": 0.050562499999999955,
				"x": 0.39408333333333334,
				"y": 0.11001562499999998
			}
		},
		{
			"class_idx": 1,
			"name": "Bella",
			"points": [
				{
					"int_x": 344,
					"int_y": 160,
					"x": 0.3578541666666667,
					"y": 0.12483203125
				},
				{
					"int_x": 381,
					"int_y": 160,
					"x": 0.3971458333333333,
					"y": 0.12483203125
				},
				{
					"int_x": 381,
					"int_y": 259,
					"x": 0.3971458333333333,
					"y": 0.20198046875
				},
				{
					"int_x": 344,
					"int_y": 259,
					"x": 0.3578541666666667,
					"y": 0.20198046875
				}
			],
			"rect": {
				"h": 0.0771484375,
				"int_h": 100,
				"int_w": 38,
				"int_x": 344,
				"int_y": 160,
				"w": 0.039291666666666614,
				"x": 0.3578541666666667,
				"y": 0.12483203125
			}
		},
		{
			"class_idx": 1,
			"name": "Bella",
			"points": [
				{
					"int_x": 428,
					"int_y": 153,
					"x": 0.44621354166666666,
					"y": 0.11956640625
				},
				{
					"int_x": 476,
					"int_y": 153,
					"x": 0.4957447916666667,
					"y": 0.11956640625
				},
				{
					"int_x": 476,
					"int_y": 255,
					"x": 0.4957447916666667,
					"y": 0.19888671875
				},
				{
					"int_x": 428,
					"int_y": 255,
					"x": 0.44621354166666666,
					"y": 0.19888671875
				}
			],
			"rect": {
				"h": 0.07932031249999999,
				"int_h": 103,
				"int_w": 49,
				"int_x": 428,
				"int_y": 153,
				"w": 0.04953125000000003,
				"x": 0.44621354166666666,
				"y": 0.11956640625
			}
		},
		{
			"class_idx": 1,
			"name": "Bella",
			"points": [
				{
					"int_x": 480,
					"int_y": 151,
					"x": 0.49996354166666673,
					"y": 0.1176953125
				},
				{
					"int_x": 527,
					"int_y": 151,
					"x": 0.5493489583333334,
					"y": 0.1176953125
				},
				{
					"int_x": 527,
					"int_y": 250,
					"x": 0.5493489583333334,
					"y": 0.19525781250000002
				},
				{
					"int_x": 480,
					"int_y": 250,
					"x": 0.49996354166666673,
					"y": 0.19525781250000002
				}
			],
			"rect": {
				"h": 0.07756250000000002,
				"int_h": 100,
				"int_w": 48,
				"int_x": 480,
				"int_y": 151,
				"w": 0.04938541666666668,
				"x": 0.49996354166666673,
				"y": 0.1176953125
			}
		},
		{
			"class_idx": 1,
			"name": "Bella",
			"points": [
				{
					"int_x": 526,
					"int_y": 145,
					"x": 0.5481302083333335,
					"y": 0.11351953125
				},
				{
					"int_x": 574,
					"int_y": 145,
					"x": 0.5980989583333334,
					"y": 0.11351953125
				},
				{
					"int_x": 574,
					"int_y": 247,
					"x": 0.5980989583333334,
					"y": 0.19321484375
				},
				{
					"int_x": 526,
					"int_y": 247,
					"x": 0.5481302083333335,
					"y": 0.19321484375
				}
			],
			"rect": {
				"h": 0.0796953125,
				"int_h": 103,
				"int_w": 49,
				"int_x": 526,
				"int_y": 145,
				"w": 0.049968749999999895,
				"x": 0.5481302083333335,
				"y": 0.11351953125
			}
		},
		{
			"class_idx": 1,
			"name": "Bella",
			"points": [
				{
					"int_x": 576,
					"int_y": 148,
					"x": 0.5998802083333333,
					"y": 0.11599609375
				},
				{
					"int_x": 625,
					"int_y": 148,
					"x": 0.6511614583333333,
					"y": 0.11599609375
				},
				{
					"int_x": 625,
					"int_y": 248,
					"x": 0.6511614583333333,
					"y": 0.19400390625
				},
				{
					"int_x": 576,
					"int_y": 248,
					"x": 0.5998802083333333,
					"y": 0.19400390625
				}
			],
			"rect": {
				"h": 0.0780078125,
				"int_h": 101,
				"int_w": 50,
				"int_x": 576,
				"int_y": 148,
				"w": 0.051281249999999945,
				"x": 0.5998802083333333,
				"y": 0.11599609375
			}
		},
		{
			"class_idx": 1,
			"name": "Bella",
			"points": [
				{
					"int_x": 230,
					"int_y": 252,
					"x": 0.23926041666666664,
					"y": 0.19695703125
				},
				{
					"int_x": 294,
					"int_y": 252,
					"x": 0.30596875,
					"y": 0.19695703125
				},
				{
					"int_x": 294,
					"int_y": 319,
					"x": 0.30596875,
					"y": 0.24924609374999998
				},
				{
					"int_x": 230,
					"int_y": 319,
					"x": 0.23926041666666664,
					"y": 0.24924609374999998
				}
			],
			"rect": {
				"h": 0.05228906249999998,
				"int_h": 68,
				"int_w": 65,
				"int_x": 230,
				"int_y": 252,
				"w": 0.06670833333333337,
				"x": 0.23926041666666664,
				"y": 0.19695703125
			}
		},
		{
			"class_idx": 1,
			"name": "Bella",
			"points": [
				{
					"int_x": 292,
					"int_y": 244,
					"x": 0.30441145833333333,
					"y": 0.19033203125
				},
				{
					"int_x": 365,
					"int_y": 244,
					"x": 0.379921875,
					"y": 0.19033203125
				},
				{
					"int_x": 365,
					"int_y": 317,
					"x": 0.379921875,
					"y": 0.24801171875000003
				},
				{
					"int_x": 292,
					"int_y": 317,
					"x": 0.30441145833333333,
					"y": 0.24801171875000003
				}
			],
			"rect": {
				"h": 0.05767968750000002,
				"int_h": 74,
				"int_w": 74,
				"int_x": 292,
				"int_y": 244,
				"w": 0.07551041666666669,
				"x": 0.30441145833333333,
				"y": 0.19033203125
			}
		},
		{
			"class_idx": 1,
			"name": "Bella",
			"points": [
				{
					"int_x": 369,
					"int_y": 260,
					"x": 0.38469791666666664,
					"y": 0.20287890625000002
				},
				{
					"int_x": 432,
					"int_y": 260,
					"x": 0.44996875000000003,
					"y": 0.20287890625000002
				},
				{
					"int_x": 432,
					"int_y": 323,
					"x": 0.44996875000000003,
					"y": 0.25205859375
				},
				{
					"int_x": 369,
					"int_y": 323,
					"x": 0.38469791666666664,
					"y": 0.25205859375
				}
			],
			"rect": {
				"h": 0.049179687499999986,
				"int_h": 64,
				"int_w": 64,
				"int_x": 369,
				"int_y": 260,
				"w": 0.06527083333333339,
				"x": 0.38469791666666664,
				"y": 0.20287890625000002
			}
		},
		{
			"class_idx": 1,
			"name": "Bella",
			"points": [
				{
					"int_x": 431,
					"int_y": 256,
					"x": 0.44844270833333333,
					"y": 0.20028125000000002
				},
				{
					"int_x": 496,
					"int_y": 256,
					"x": 0.5166197916666667,
					"y": 0.20028125000000002
				},
				{
					"int_x": 496,
					"int_y": 321,
					"x": 0.5166197916666667,
					"y": 0.250859375
				},
				{
					"int_x": 431,
					"int_y": 321,
					"x": 0.44844270833333333,
					"y": 0.250859375
				}
			],
			"rect": {
				"h": 0.050578124999999974,
				"int_h": 66,
				"int_w": 66,
				"int_x": 431,
				"int_y": 256,
				"w": 0.06817708333333339,
				"x": 0.44844270833333333,
				"y": 0.20028125000000002
			}
		},
		{
			"class_idx": 1,
			"name": "Bella",
			"points": [
				{
					"int_x": 497,
					"int_y": 250,
					"x": 0.5177760416666667,
					"y": 0.19504296875
				},
				{
					"int_x": 562,
					"int_y": 250,
					"x": 0.5852864583333334,
					"y": 0.19504296875
				},
				{
					"int_x": 562,
					"int_y": 319,
					"x": 0.5852864583333334,
					"y": 0.24891015625000001
				},
				{
					"int_x": 497,
					"int_y": 319,
					"x": 0.5177760416666667,
					"y": 0.24891015625000001
				}
			],
			"rect": {
				"h": 0.053867187500000024,
				"int_h": 70,
				"int_w": 66,
				"int_x": 497,
				"int_y": 250,
				"w": 0.06751041666666668,
				"x": 0.5177760416666667,
				"y": 0.19504296875
			}
		},
		{
			"class_idx": 1,
			"name": "Bella",
			"points": [
				{
					"int_x": 561,
					"int_y": 250,
					"x": 0.5842083333333333,
					"y": 0.19567968749999998
				},
				{
					"int_x": 630,
					"int_y": 250,
					"x": 0.6561875,
					"y": 0.19567968749999998
				},
				{
					"int_x": 630,
					"int_y": 314,
					"x": 0.6561875,
					"y": 0.2455703125
				},
				{
					"int_x": 561,
					"int_y": 314,
					"x": 0.5842083333333333,
					"y": 0.2455703125
				}
			],
			"rect": {
				"h": 0.04989062500000002,
				"int_h": 65,
				"int_w": 70,
				"int_x": 561,
				"int_y": 250,
				"w": 0.0719791666666667,
				"x": 0.5842083333333333,
				"y": 0.19567968749999998
			}
		},
		{
			"class_idx": 6,
			"name": "Libresse",
			"points": [
				{
					"int_x": 798,
					"int_y": 229,
					"x": 0.8310364583333333,
					"y": 0.178921875
				},
				{
					"int_x": 892,
					"int_y": 229,
					"x": 0.929234375,
					"y": 0.178921875
				},
				{
					"int_x": 892,
					"int_y": 367,
					"x": 0.929234375,
					"y": 0.286328125
				},
				{
					"int_x": 798,
					"int_y": 367,
					"x": 0.8310364583333333,
					"y": 0.286328125
				}
			],
			"rect": {
				"h": 0.10740624999999998,
				"int_h": 139,
				"int_w": 95,
				"int_x": 798,
				"int_y": 229,
				"w": 0.09819791666666666,
				"x": 0.8310364583333333,
				"y": 0.178921875
			}
		},
		{
			"class_idx": 1,
			"name": "Bella",
			"points": [
				{
					"int_x": 233,
					"int_y": 321,
					"x": 0.24219791666666668,
					"y": 0.2506484375
				},
				{
					"int_x": 298,
					"int_y": 321,
					"x": 0.3105104166666667,
					"y": 0.2506484375
				},
				{
					"int_x": 298,
					"int_y": 380,
					"x": 0.3105104166666667,
					"y": 0.2971328125
				},
				{
					"int_x": 233,
					"int_y": 380,
					"x": 0.24219791666666668,
					"y": 0.2971328125
				}
			],
			"rect": {
				"h": 0.04648437500000002,
				"int_h": 60,
				"int_w": 66,
				"int_x": 233,
				"int_y": 321,
				"w": 0.0683125,
				"x": 0.24219791666666668,
				"y": 0.2506484375
			}
		},
		{
			"class_idx": 1,
			"name": "Bella",
			"points": [
				{
					"int_x": 299,
					"int_y": 317,
					"x": 0.31116666666666665,
					"y": 0.24747265624999998
				},
				{
					"int_x": 370,
					"int_y": 317,
					"x": 0.38585416666666666,
					"y": 0.24747265624999998
				},
				{
					"int_x": 370,
					"int_y": 384,
					"x": 0.38585416666666666,
					"y": 0.29971484374999996
				},
				{
					"int_x": 299,
					"int_y": 384,
					"x": 0.31116666666666665,
					"y": 0.29971484374999996
				}
			],
			"rect": {
				"h": 0.05224218749999998,
				"int_h": 68,
				"int_w": 72,
				"int_x": 299,
				"int_y": 317,
				"w": 0.07468750000000002,
				"x": 0.31116666666666665,
				"y": 0.24747265624999998
			}
		},
		{
			"class_idx": 1,
			"name": "Bella",
			"points": [
				{
					"int_x": 371,
					"int_y": 325,
					"x": 0.3864166666666667,
					"y": 0.25415234375
				},
				{
					"int_x": 432,
					"int_y": 325,
					"x": 0.45,
					"y": 0.25415234375
				},
				{
					"int_x": 432,
					"int_y": 384,
					"x": 0.45,
					"y": 0.29966015625000003
				},
				{
					"int_x": 371,
					"int_y": 384,
					"x": 0.3864166666666667,
					"y": 0.29966015625000003
				}
			],
			"rect": {
				"h": 0.04550781250000002,
				"int_h": 60,
				"int_w": 62,
				"int_x": 371,
				"int_y": 325,
				"w": 0.06358333333333333,
				"x": 0.3864166666666667,
				"y": 0.25415234375
			}
		},
		{
			"class_idx": 1,
			"name": "Bella",
			"points": [
				{
					"int_x": 433,
					"int_y": 325,
					"x": 0.45072395833333334,
					"y": 0.25371484375
				},
				{
					"int_x": 498,
					"int_y": 325,
					"x": 0.518546875,
					"y": 0.25371484375
				},
				{
					"int_x": 498,
					"int_y": 383,
					"x": 0.518546875,
					"y": 0.29955078125
				},
				{
					"int_x": 433,
					"int_y": 383,
					"x": 0.45072395833333334,
					"y": 0.29955078125
				}
			],
			"rect": {
				"h": 0.045835937500000035,
				"int_h": 59,
				"int_w": 66,
				"int_x": 433,
				"int_y": 325,
				"w": 0.06782291666666662,
				"x": 0.45072395833333334,
				"y": 0.25371484375
			}
		},
		{
			"class_idx": 1,
			"name": "Bella",
			"points": [
				{
					"int_x": 498,
					"int_y": 318,
					"x": 0.5190885416666667,
					"y": 0.24845703125000002
				},
				{
					"int_x": 565,
					"int_y": 318,
					"x": 0.5880781250000001,
					"y": 0.24845703125000002
				},
				{
					"int_x": 565,
					"int_y": 384,
					"x": 0.5880781250000001,
					"y": 0.29983984375
				},
				{
					"int_x": 498,
					"int_y": 384,
					"x": 0.5190885416666667,
					"y": 0.29983984375
				}
			],
			"rect": {
				"h": 0.051382812499999986,
				"int_h": 67,
				"int_w": 68,
				"int_x": 498,
				"int_y": 318,
				"w": 0.06898958333333338,
				"x": 0.5190885416666667,
				"y": 0.24845703125000002
			}
		},
		{
			"class_idx": 1,
			"name": "Bella",
			"points": [
				{
					"int_x": 562,
					"int_y": 317,
					"x": 0.5855624999999999,
					"y": 0.24763671875
				},
				{
					"int_x": 629,
					"int_y": 317,
					"x": 0.6551874999999999,
					"y": 0.24763671875
				},
				{
					"int_x": 629,
					"int_y": 379,
					"x": 0.6551874999999999,
					"y": 0.29622265625
				},
				{
					"int_x": 562,
					"int_y": 379,
					"x": 0.5855624999999999,
					"y": 0.29622265625
				}
			],
			"rect": {
				"h": 0.04858593749999998,
				"int_h": 63,
				"int_w": 68,
				"int_x": 562,
				"int_y": 317,
				"w": 0.06962500000000005,
				"x": 0.5855624999999999,
				"y": 0.24763671875
			}
		},
		{
			"class_idx": 6,
			"name": "Libresse",
			"points": [
				{
					"int_x": 649,
					"int_y": 231,
					"x": 0.6762291666666667,
					"y": 0.18066015625000004
				},
				{
					"int_x": 718,
					"int_y": 231,
					"x": 0.7476875000000001,
					"y": 0.18066015625000004
				},
				{
					"int_x": 718,
					"int_y": 373,
					"x": 0.7476875000000001,
					"y": 0.29157421875
				},
				{
					"int_x": 649,
					"int_y": 373,
					"x": 0.6762291666666667,
					"y": 0.29157421875
				}
			],
			"rect": {
				"h": 0.11091406249999997,
				"int_h": 143,
				"int_w": 70,
				"int_x": 649,
				"int_y": 231,
				"w": 0.0714583333333334,
				"x": 0.6762291666666667,
				"y": 0.18066015625000004
			}
		},
		{
			"class_idx": 6,
			"name": "Libresse",
			"points": [
				{
					"int_x": 717,
					"int_y": 237,
					"x": 0.7464010416666667,
					"y": 0.18519140624999997
				},
				{
					"int_x": 785,
					"int_y": 237,
					"x": 0.8178697916666666,
					"y": 0.18519140624999997
				},
				{
					"int_x": 785,
					"int_y": 375,
					"x": 0.8178697916666666,
					"y": 0.29277734375
				},
				{
					"int_x": 717,
					"int_y": 375,
					"x": 0.7464010416666667,
					"y": 0.29277734375
				}
			],
			"rect": {
				"h": 0.1075859375,
				"int_h": 139,
				"int_w": 69,
				"int_x": 717,
				"int_y": 237,
				"w": 0.07146874999999997,
				"x": 0.7464010416666667,
				"y": 0.18519140624999997
			}
		},
		{
			"class_idx": 6,
			"name": "Libresse",
			"points": [
				{
					"int_x": 883,
					"int_y": 234,
					"x": 0.9201770833333334,
					"y": 0.18287890624999997
				},
				{
					"int_x": 953,
					"int_y": 234,
					"x": 0.9930729166666667,
					"y": 0.18287890624999997
				},
				{
					"int_x": 953,
					"int_y": 380,
					"x": 0.9930729166666667,
					"y": 0.29671484375
				},
				{
					"int_x": 883,
					"int_y": 380,
					"x": 0.9201770833333334,
					"y": 0.29671484375
				}
			],
			"rect": {
				"h": 0.11383593750000004,
				"int_h": 147,
				"int_w": 71,
				"int_x": 883,
				"int_y": 234,
				"w": 0.07289583333333338,
				"x": 0.9201770833333334,
				"y": 0.18287890624999997
			}
		},
		{
			"class_idx": 1,
			"name": "Bella",
			"points": [
				{
					"int_x": 244,
					"int_y": 398,
					"x": 0.25414062499999995,
					"y": 0.31077734375
				},
				{
					"int_x": 315,
					"int_y": 398,
					"x": 0.32821354166666666,
					"y": 0.31077734375
				},
				{
					"int_x": 315,
					"int_y": 458,
					"x": 0.32821354166666666,
					"y": 0.35801953124999997
				},
				{
					"int_x": 244,
					"int_y": 458,
					"x": 0.25414062499999995,
					"y": 0.35801953124999997
				}
			],
			"rect": {
				"h": 0.04724218749999998,
				"int_h": 61,
				"int_w": 72,
				"int_x": 244,
				"int_y": 398,
				"w": 0.07407291666666671,
				"x": 0.25414062499999995,
				"y": 0.31077734375
			}
		},
		{
			"class_idx": 1,
			"name": "Bella",
			"points": [
				{
					"int_x": 318,
					"int_y": 394,
					"x": 0.33075,
					"y": 0.30816796874999997
				},
				{
					"int_x": 389,
					"int_y": 394,
					"x": 0.40531249999999996,
					"y": 0.30816796874999997
				},
				{
					"int_x": 389,
					"int_y": 453,
					"x": 0.40531249999999996,
					"y": 0.35351953125
				},
				{
					"int_x": 318,
					"int_y": 453,
					"x": 0.33075,
					"y": 0.35351953125
				}
			],
			"rect": {
				"h": 0.04535156250000005,
				"int_h": 60,
				"int_w": 72,
				"int_x": 318,
				"int_y": 394,
				"w": 0.07456249999999998,
				"x": 0.33075,
				"y": 0.30816796874999997
			}
		},
		{
			"class_idx": 1,
			"name": "Bella",
			"points": [
				{
					"int_x": 394,
					"int_y": 394,
					"x": 0.4107864583333334,
					"y": 0.30785937500000005
				},
				{
					"int_x": 468,
					"int_y": 394,
					"x": 0.48706770833333335,
					"y": 0.30785937500000005
				},
				{
					"int_x": 468,
					"int_y": 460,
					"x": 0.48706770833333335,
					"y": 0.359046875
				},
				{
					"int_x": 394,
					"int_y": 460,
					"x": 0.4107864583333334,
					"y": 0.359046875
				}
			],
			"rect": {
				"h": 0.05118749999999994,
				"int_h": 67,
				"int_w": 75,
				"int_x": 394,
				"int_y": 394,
				"w": 0.07628124999999997,
				"x": 0.4107864583333334,
				"y": 0.30785937500000005
			}
		},
		{
			"class_idx": 1,
			"name": "Bella",
			"points": [
				{
					"int_x": 471,
					"int_y": 393,
					"x": 0.49050000000000005,
					"y": 0.306765625
				},
				{
					"int_x": 548,
					"int_y": 393,
					"x": 0.5711875000000001,
					"y": 0.306765625
				},
				{
					"int_x": 548,
					"int_y": 451,
					"x": 0.5711875000000001,
					"y": 0.35215625
				},
				{
					"int_x": 471,
					"int_y": 451,
					"x": 0.49050000000000005,
					"y": 0.35215625
				}
			],
			"rect": {
				"h": 0.04539062500000002,
				"int_h": 59,
				"int_w": 78,
				"int_x": 471,
				"int_y": 393,
				"w": 0.08068750000000002,
				"x": 0.49050000000000005,
				"y": 0.306765625
			}
		},
		{
			"class_idx": 1,
			"name": "Bella",
			"points": [
				{
					"int_x": 547,
					"int_y": 385,
					"x": 0.5695104166666667,
					"y": 0.30064453124999996
				},
				{
					"int_x": 631,
					"int_y": 385,
					"x": 0.6574479166666667,
					"y": 0.30064453124999996
				},
				{
					"int_x": 631,
					"int_y": 450,
					"x": 0.6574479166666667,
					"y": 0.35173046874999997
				},
				{
					"int_x": 547,
					"int_y": 450,
					"x": 0.5695104166666667,
					"y": 0.35173046874999997
				}
			],
			"rect": {
				"h": 0.05108593750000001,
				"int_h": 66,
				"int_w": 85,
				"int_x": 547,
				"int_y": 385,
				"w": 0.0879375,
				"x": 0.5695104166666667,
				"y": 0.30064453124999996
			}
		},
		{
			"class_idx": 5,
			"name": "Kotex",
			"points": [
				{
					"int_x": 642,
					"int_y": 411,
					"x": 0.6690677083333333,
					"y": 0.321390625
				},
				{
					"int_x": 690,
					"int_y": 411,
					"x": 0.7186197916666667,
					"y": 0.321390625
				},
				{
					"int_x": 690,
					"int_y": 519,
					"x": 0.7186197916666667,
					"y": 0.40520312499999994
				},
				{
					"int_x": 642,
					"int_y": 519,
					"x": 0.6690677083333333,
					"y": 0.40520312499999994
				}
			],
			"rect": {
				"h": 0.08381249999999996,
				"int_h": 109,
				"int_w": 49,
				"int_x": 642,
				"int_y": 411,
				"w": 0.049552083333333385,
				"x": 0.6690677083333333,
				"y": 0.321390625
			}
		},
		{
			"class_idx": 5,
			"name": "Kotex",
			"points": [
				{
					"int_x": 688,
					"int_y": 416,
					"x": 0.7166770833333334,
					"y": 0.32482421875
				},
				{
					"int_x": 733,
					"int_y": 416,
					"x": 0.7640312499999999,
					"y": 0.32482421875
				},
				{
					"int_x": 733,
					"int_y": 520,
					"x": 0.7640312499999999,
					"y": 0.40625390625
				},
				{
					"int_x": 688,
					"int_y": 520,
					"x": 0.7166770833333334,
					"y": 0.40625390625
				}
			],
			"rect": {
				"h": 0.08142968750000001,
				"int_h": 105,
				"int_w": 46,
				"int_x": 688,
				"int_y": 416,
				"w": 0.047354166666666586,
				"x": 0.7166770833333334,
				"y": 0.32482421875
			}
		},
		{
			"class_idx": 5,
			"name": "Kotex",
			"points": [
				{
					"int_x": 734,
					"int_y": 410,
					"x": 0.764109375,
					"y": 0.32064453125
				},
				{
					"int_x": 782,
					"int_y": 410,
					"x": 0.814765625,
					"y": 0.32064453125
				},
				{
					"int_x": 782,
					"int_y": 519,
					"x": 0.814765625,
					"y": 0.40566796874999994
				},
				{
					"int_x": 734,
					"int_y": 519,
					"x": 0.764109375,
					"y": 0.40566796874999994
				}
			],
			"rect": {
				"h": 0.08502343749999997,
				"int_h": 110,
				"int_w": 49,
				"int_x": 734,
				"int_y": 410,
				"w": 0.05065625000000007,
				"x": 0.764109375,
				"y": 0.32064453125
			}
		},
		{
			"class_idx": 5,
			"name": "Kotex",
			"points": [
				{
					"int_x": 823,
					"int_y": 411,
					"x": 0.8572708333333333,
					"y": 0.32144921875
				},
				{
					"int_x": 895,
					"int_y": 411,
					"x": 0.9319166666666666,
					"y": 0.32144921875
				},
				{
					"int_x": 895,
					"int_y": 448,
					"x": 0.9319166666666666,
					"y": 0.34995703125
				},
				{
					"int_x": 823,
					"int_y": 448,
					"x": 0.8572708333333333,
					"y": 0.34995703125
				}
			],
			"rect": {
				"h": 0.028507812500000007,
				"int_h": 38,
				"int_w": 73,
				"int_x": 823,
				"int_y": 411,
				"w": 0.0746458333333333,
				"x": 0.8572708333333333,
				"y": 0.32144921875
			}
		},
		{
			"class_idx": 5,
			"name": "Kotex",
			"points": [
				{
					"int_x": 821,
					"int_y": 449,
					"x": 0.85490625,
					"y": 0.35056640625
				},
				{
					"int_x": 899,
					"int_y": 449,
					"x": 0.9365104166666667,
					"y": 0.35056640625
				},
				{
					"int_x": 899,
					"int_y": 484,
					"x": 0.9365104166666667,
					"y": 0.37832421875
				},
				{
					"int_x": 821,
					"int_y": 484,
					"x": 0.85490625,
					"y": 0.37832421875
				}
			],
			"rect": {
				"h": 0.02775781249999998,
				"int_h": 36,
				"int_w": 79,
				"int_x": 821,
				"int_y": 449,
				"w": 0.0816041666666667,
				"x": 0.85490625,
				"y": 0.35056640625
			}
		},
		{
			"class_idx": 5,
			"name": "Kotex",
			"points": [
				{
					"int_x": 901,
					"int_y": 446,
					"x": 0.9385989583333333,
					"y": 0.3482421875
				},
				{
					"int_x": 960,
					"int_y": 446,
					"x": 1.0,
					"y": 0.3482421875
				},
				{
					"int_x": 960,
					"int_y": 484,
					"x": 1.0,
					"y": 0.3777890625
				},
				{
					"int_x": 901,
					"int_y": 484,
					"x": 0.9385989583333333,
					"y": 0.3777890625
				}
			],
			"rect": {
				"h": 0.029546874999999972,
				"int_h": 39,
				"int_w": 59,
				"int_x": 901,
				"int_y": 446,
				"w": 0.06140104166666671,
				"x": 0.9385989583333333,
				"y": 0.3482421875
			}
		},
		{
			"class_idx": 5,
			"name": "Kotex",
			"points": [
				{
					"int_x": 903,
					"int_y": 412,
					"x": 0.9410416666666667,
					"y": 0.32168749999999996
				},
				{
					"int_x": 960,
					"int_y": 412,
					"x": 0.99975,
					"y": 0.32168749999999996
				},
				{
					"int_x": 960,
					"int_y": 443,
					"x": 0.99975,
					"y": 0.34631249999999997
				},
				{
					"int_x": 903,
					"int_y": 443,
					"x": 0.9410416666666667,
					"y": 0.34631249999999997
				}
			],
			"rect": {
				"h": 0.024625000000000008,
				"int_h": 32,
				"int_w": 57,
				"int_x": 903,
				"int_y": 412,
				"w": 0.05870833333333336,
				"x": 0.9410416666666667,
				"y": 0.32168749999999996
			}
		},
		{
			"class_idx": 1,
			"name": "Bella",
			"points": [
				{
					"int_x": 244,
					"int_y": 459,
					"x": 0.25441145833333334,
					"y": 0.35842578125
				},
				{
					"int_x": 318,
					"int_y": 459,
					"x": 0.331546875,
					"y": 0.35842578125
				},
				{
					"int_x": 318,
					"int_y": 519,
					"x": 0.331546875,
					"y": 0.40552734375
				},
				{
					"int_x": 244,
					"int_y": 519,
					"x": 0.25441145833333334,
					"y": 0.40552734375
				}
			],
			"rect": {
				"h": 0.04710156249999997,
				"int_h": 61,
				"int_w": 75,
				"int_x": 244,
				"int_y": 459,
				"w": 0.07713541666666668,
				"x": 0.25441145833333334,
				"y": 0.35842578125
			}
		},
		{
			"class_idx": 1,
			"name": "Bella",
			"points": [
				{
					"int_x": 316,
					"int_y": 458,
					"x": 0.3294270833333333,
					"y": 0.35743749999999996
				},
				{
					"int_x": 388,
					"int_y": 458,
					"x": 0.4043229166666667,
					"y": 0.35743749999999996
				},
				{
					"int_x": 388,
					"int_y": 519,
					"x": 0.4043229166666667,
					"y": 0.405109375
				},
				{
					"int_x": 316,
					"int_y": 519,
					"x": 0.3294270833333333,
					"y": 0.405109375
				}
			],
			"rect": {
				"h": 0.04767187500000003,
				"int_h": 62,
				"int_w": 73,
				"int_x": 316,
				"int_y": 458,
				"w": 0.07489583333333338,
				"x": 0.3294270833333333,
				"y": 0.35743749999999996
			}
		},
		{
			"class_idx": 1,
			"name": "Bella",
			"points": [
				{
					"int_x": 394,
					"int_y": 459,
					"x": 0.4109322916666666,
					"y": 0.35855859375
				},
				{
					"int_x": 469,
					"int_y": 459,
					"x": 0.4880677083333333,
					"y": 0.35855859375
				},
				{
					"int_x": 469,
					"int_y": 518,
					"x": 0.4880677083333333,
					"y": 0.40458203125000003
				},
				{
					"int_x": 394,
					"int_y": 518,
					"x": 0.4109322916666666,
					"y": 0.40458203125000003
				}
			],
			"rect": {
				"h": 0.04602343750000004,
				"int_h": 60,
				"int_w": 76,
				"int_x": 394,
				"int_y": 459,
				"w": 0.07713541666666668,
				"x": 0.4109322916666666,
				"y": 0.35855859375
			}
		},
		{
			"class_idx": 1,
			"name": "Bella",
			"points": [
				{
					"int_x": 471,
					"int_y": 457,
					"x": 0.49097395833333335,
					"y": 0.35729296875000005
				},
				{
					"int_x": 548,
					"int_y": 457,
					"x": 0.570421875,
					"y": 0.35729296875000005
				},
				{
					"int_x": 548,
					"int_y": 518,
					"x": 0.570421875,
					"y": 0.40467578125000003
				},
				{
					"int_x": 471,
					"int_y": 518,
					"x": 0.49097395833333335,
					"y": 0.40467578125000003
				}
			],
			"rect": {
				"h": 0.04738281249999998,
				"int_h": 62,
				"int_w": 78,
				"int_x": 471,
				"int_y": 457,
				"w": 0.07944791666666662,
				"x": 0.49097395833333335,
				"y": 0.35729296875000005
			}
		},
		{
			"class_idx": 1,
			"name": "Bella",
			"points": [
				{
					"int_x": 548,
					"int_y": 454,
					"x": 0.571109375,
					"y": 0.35475390625
				},
				{
					"int_x": 630,
					"int_y": 454,
					"x": 0.656765625,
					"y": 0.35475390625
				},
				{
					"int_x": 630,
					"int_y": 517,
					"x": 0.656765625,
					"y": 0.40426171875
				},
				{
					"int_x": 548,
					"int_y": 517,
					"x": 0.571109375,
					"y": 0.40426171875
				}
			],
			"rect": {
				"h": 0.049507812500000026,
				"int_h": 64,
				"int_w": 83,
				"int_x": 548,
				"int_y": 454,
				"w": 0.08565624999999999,
				"x": 0.571109375,
				"y": 0.35475390625
			}
		},
		{
			"class_idx": 5,
			"name": "Kotex",
			"points": [
				{
					"int_x": 782,
					"int_y": 420,
					"x": 0.8142916666666666,
					"y": 0.3285078125
				},
				{
					"int_x": 818,
					"int_y": 420,
					"x": 0.8519166666666667,
					"y": 0.3285078125
				},
				{
					"int_x": 818,
					"int_y": 522,
					"x": 0.8519166666666667,
					"y": 0.40746093749999995
				},
				{
					"int_x": 782,
					"int_y": 522,
					"x": 0.8142916666666666,
					"y": 0.40746093749999995
				}
			],
			"rect": {
				"h": 0.07895312499999996,
				"int_h": 103,
				"int_w": 37,
				"int_x": 782,
				"int_y": 420,
				"w": 0.03762500000000002,
				"x": 0.8142916666666666,
				"y": 0.3285078125
			}
		},
		{
			"class_idx": 5,
			"name": "Kotex",
			"points": [
				{
					"int_x": 820,
					"int_y": 484,
					"x": 0.8543489583333334,
					"y": 0.37815624999999997
				},
				{
					"int_x": 898,
					"int_y": 484,
					"x": 0.9354427083333333,
					"y": 0.37815624999999997
				},
				{
					"int_x": 898,
					"int_y": 521,
					"x": 0.9354427083333333,
					"y": 0.40665624999999994
				},
				{
					"int_x": 820,
					"int_y": 521,
					"x": 0.8543489583333334,
					"y": 0.40665624999999994
				}
			],
			"rect": {
				"h": 0.02849999999999997,
				"int_h": 38,
				"int_w": 79,
				"int_x": 820,
				"int_y": 484,
				"w": 0.08109374999999996,
				"x": 0.8543489583333334,
				"y": 0.37815624999999997
			}
		},
		{
			"class_idx": 5,
			"name": "Kotex",
			"points": [
				{
					"int_x": 898,
					"int_y": 485,
					"x": 0.9357864583333333,
					"y": 0.37864062499999995
				},
				{
					"int_x": 960,
					"int_y": 485,
					"x": 1.0,
					"y": 0.37864062499999995
				},
				{
					"int_x": 960,
					"int_y": 519,
					"x": 1.0,
					"y": 0.40534375
				},
				{
					"int_x": 898,
					"int_y": 519,
					"x": 0.9357864583333333,
					"y": 0.40534375
				}
			],
			"rect": {
				"h": 0.02670312500000005,
				"int_h": 35,
				"int_w": 62,
				"int_x": 898,
				"int_y": 485,
				"w": 0.06421354166666671,
				"x": 0.9357864583333333,
				"y": 0.37864062499999995
			}
		},
		{
			"class_idx": 1,
			"name": "Bella",
			"points": [
				{
					"int_x": 242,
					"int_y": 554,
					"x": 0.2523229166666667,
					"y": 0.43262109375
				},
				{
					"int_x": 309,
					"int_y": 554,
					"x": 0.32146875,
					"y": 0.43262109375
				},
				{
					"int_x": 309,
					"int_y": 613,
					"x": 0.32146875,
					"y": 0.47897265624999996
				},
				{
					"int_x": 242,
					"int_y": 613,
					"x": 0.2523229166666667,
					"y": 0.47897265624999996
				}
			],
			"rect": {
				"h": 0.04635156249999994,
				"int_h": 60,
				"int_w": 68,
				"int_x": 242,
				"int_y": 554,
				"w": 0.06914583333333335,
				"x": 0.2523229166666667,
				"y": 0.43262109375
			}
		},
		{
			"class_idx": 1,
			"name": "Bella",
			"points": [
				{
					"int_x": 313,
					"int_y": 544,
					"x": 0.3257291666666667,
					"y": 0.424921875
				},
				{
					"int_x": 383,
					"int_y": 544,
					"x": 0.3988541666666667,
					"y": 0.424921875
				},
				{
					"int_x": 383,
					"int_y": 671,
					"x": 0.3988541666666667,
					"y": 0.523828125
				},
				{
					"int_x": 313,
					"int_y": 671,
					"x": 0.3257291666666667,
					"y": 0.523828125
				}
			],
			"rect": {
				"h": 0.09890624999999997,
				"int_h": 128,
				"int_w": 71,
				"int_x": 313,
				"int_y": 544,
				"w": 0.073125,
				"x": 0.3257291666666667,
				"y": 0.424921875
			}
		},
		{
			"class_idx": 1,
			"name": "Bella",
			"points": [
				{
					"int_x": 385,
					"int_y": 545,
					"x": 0.400625,
					"y": 0.42578125
				},
				{
					"int_x": 448,
					"int_y": 545,
					"x": 0.46687500000000004,
					"y": 0.42578125
				},
				{
					"int_x": 448,
					"int_y": 665,
					"x": 0.46687500000000004,
					"y": 0.51984375
				},
				{
					"int_x": 385,
					"int_y": 665,
					"x": 0.400625,
					"y": 0.51984375
				}
			],
			"rect": {
				"h": 0.09406250000000005,
				"int_h": 121,
				"int_w": 64,
				"int_x": 385,
				"int_y": 545,
				"w": 0.06625000000000003,
				"x": 0.400625,
				"y": 0.42578125
			}
		},
		{
			"class_idx": 1,
			"name": "Bella",
			"points": [
				{
					"int_x": 450,
					"int_y": 542,
					"x": 0.4686458333333333,
					"y": 0.423671875
				},
				{
					"int_x": 516,
					"int_y": 542,
					"x": 0.5371875,
					"y": 0.423671875
				},
				{
					"int_x": 516,
					"int_y": 667,
					"x": 0.5371875,
					"y": 0.5213281249999999
				},
				{
					"int_x": 450,
					"int_y": 667,
					"x": 0.4686458333333333,
					"y": 0.5213281249999999
				}
			],
			"rect": {
				"h": 0.09765624999999994,
				"int_h": 126,
				"int_w": 67,
				"int_x": 450,
				"int_y": 542,
				"w": 0.06854166666666672,
				"x": 0.4686458333333333,
				"y": 0.423671875
			}
		},
		{
			"class_idx": 1,
			"name": "Bella",
			"points": [
				{
					"int_x": 516,
					"int_y": 537,
					"x": 0.5379166666666666,
					"y": 0.41945312500000004
				},
				{
					"int_x": 585,
					"int_y": 537,
					"x": 0.6095833333333334,
					"y": 0.41945312500000004
				},
				{
					"int_x": 585,
					"int_y": 667,
					"x": 0.6095833333333334,
					"y": 0.5211718750000001
				},
				{
					"int_x": 516,
					"int_y": 667,
					"x": 0.5379166666666666,
					"y": 0.5211718750000001
				}
			],
			"rect": {
				"h": 0.10171875000000002,
				"int_h": 131,
				"int_w": 70,
				"int_x": 516,
				"int_y": 537,
				"w": 0.07166666666666677,
				"x": 0.5379166666666666,
				"y": 0.41945312500000004
			}
		},
		{
			"class_idx": 5,
			"name": "Kotex",
			"points": [
				{
					"int_x": 668,
					"int_y": 556,
					"x": 0.6958229166666666,
					"y": 0.4346796875
				},
				{
					"int_x": 748,
					"int_y": 556,
					"x": 0.7795104166666665,
					"y": 0.4346796875
				},
				{
					"int_x": 748,
					"int_y": 665,
					"x": 0.7795104166666665,
					"y": 0.5198046875
				},
				{
					"int_x": 668,
					"int_y": 665,
					"x": 0.6958229166666666,
					"y": 0.5198046875
				}
			],
			"rect": {
				"h": 0.08512499999999995,
				"int_h": 110,
				"int_w": 81,
				"int_x": 668,
				"int_y": 556,
				"w": 0.08368749999999991,
				"x": 0.6958229166666666,
				"y": 0.4346796875
			}
		},
		{
			"class_idx": 5,
			"name": "Kotex",
			"points": [
				{
					"int_x": 751,
					"int_y": 557,
					"x": 0.7825364583333333,
					"y": 0.43540625
				},
				{
					"int_x": 821,
					"int_y": 557,
					"x": 0.8552552083333332,
					"y": 0.43540625
				},
				{
					"int_x": 821,
					"int_y": 665,
					"x": 0.8552552083333332,
					"y": 0.519859375
				},
				{
					"int_x": 751,
					"int_y": 665,
					"x": 0.7825364583333333,
					"y": 0.519859375
				}
			],
			"rect": {
				"h": 0.08445312500000002,
				"int_h": 109,
				"int_w": 71,
				"int_x": 751,
				"int_y": 557,
				"w": 0.07271874999999994,
				"x": 0.7825364583333333,
				"y": 0.43540625
			}
		},
		{
			"class_idx": 5,
			"name": "Kotex",
			"points": [
				{
					"int_x": 819,
					"int_y": 558,
					"x": 0.8526250000000001,
					"y": 0.43619140624999997
				},
				{
					"int_x": 881,
					"int_y": 558,
					"x": 0.917625,
					"y": 0.43619140624999997
				},
				{
					"int_x": 881,
					"int_y": 666,
					"x": 0.917625,
					"y": 0.52068359375
				},
				{
					"int_x": 819,
					"int_y": 666,
					"x": 0.8526250000000001,
					"y": 0.52068359375
				}
			],
			"rect": {
				"h": 0.08449218749999998,
				"int_h": 109,
				"int_w": 63,
				"int_x": 819,
				"int_y": 558,
				"w": 0.06499999999999995,
				"x": 0.8526250000000001,
				"y": 0.43619140624999997
			}
		},
		{
			"class_idx": 5,
			"name": "Kotex",
			"points": [
				{
					"int_x": 880,
					"int_y": 560,
					"x": 0.9169895833333334,
					"y": 0.43751562499999996
				},
				{
					"int_x": 939,
					"int_y": 560,
					"x": 0.9782604166666667,
					"y": 0.43751562499999996
				},
				{
					"int_x": 939,
					"int_y": 669,
					"x": 0.9782604166666667,
					"y": 0.5226875
				},
				{
					"int_x": 880,
					"int_y": 669,
					"x": 0.9169895833333334,
					"y": 0.5226875
				}
			],
			"rect": {
				"h": 0.08517187500000001,
				"int_h": 110,
				"int_w": 60,
				"int_x": 880,
				"int_y": 560,
				"w": 0.061270833333333385,
				"x": 0.9169895833333334,
				"y": 0.43751562499999996
			}
		},
		{
			"class_idx": 5,
			"name": "Kotex",
			"points": [
				{
					"int_x": 944,
					"int_y": 564,
					"x": 0.9830416666666666,
					"y": 0.44098046875
				},
				{
					"int_x": 960,
					"int_y": 564,
					"x": 1.0,
					"y": 0.44098046875
				},
				{
					"int_x": 960,
					"int_y": 672,
					"x": 1.0,
					"y": 0.52498828125
				},
				{
					"int_x": 944,
					"int_y": 672,
					"x": 0.9830416666666666,
					"y": 0.52498828125
				}
			],
			"rect": {
				"h": 0.08400781249999995,
				"int_h": 109,
				"int_w": 16,
				"int_x": 944,
				"int_y": 564,
				"w": 0.01695833333333341,
				"x": 0.9830416666666666,
				"y": 0.44098046875
			}
		},
		{
			"class_idx": 1,
			"name": "Bella",
			"points": [
				{
					"int_x": 249,
					"int_y": 615,
					"x": 0.25937499999999997,
					"y": 0.48078125000000005
				},
				{
					"int_x": 313,
					"int_y": 615,
					"x": 0.325625,
					"y": 0.48078125000000005
				},
				{
					"int_x": 313,
					"int_y": 674,
					"x": 0.325625,
					"y": 0.52671875
				},
				{
					"int_x": 249,
					"int_y": 674,
					"x": 0.25937499999999997,
					"y": 0.52671875
				}
			],
			"rect": {
				"h": 0.045937499999999964,
				"int_h": 60,
				"int_w": 65,
				"int_x": 249,
				"int_y": 615,
				"w": 0.06625000000000003,
				"x": 0.25937499999999997,
				"y": 0.48078125000000005
			}
		},
		{
			"class_idx": 5,
			"name": "Kotex",
			"points": [
				{
					"int_x": 712,
					"int_y": 687,
					"x": 0.7413020833333333,
					"y": 0.53642578125
				},
				{
					"int_x": 749,
					"int_y": 687,
					"x": 0.7806354166666667,
					"y": 0.53642578125
				},
				{
					"int_x": 749,
					"int_y": 717,
					"x": 0.7806354166666667,
					"y": 0.56043359375
				},
				{
					"int_x": 712,
					"int_y": 717,
					"x": 0.7413020833333333,
					"y": 0.56043359375
				}
			],
			"rect": {
				"h": 0.02400781250000006,
				"int_h": 31,
				"int_w": 38,
				"int_x": 712,
				"int_y": 687,
				"w": 0.03933333333333344,
				"x": 0.7413020833333333,
				"y": 0.53642578125
			}
		},
		{
			"class_idx": 5,
			"name": "Kotex",
			"points": [
				{
					"int_x": 648,
					"int_y": 696,
					"x": 0.6745989583333333,
					"y": 0.54345703125
				},
				{
					"int_x": 709,
					"int_y": 696,
					"x": 0.7385260416666667,
					"y": 0.54345703125
				},
				{
					"int_x": 709,
					"int_y": 741,
					"x": 0.7385260416666667,
					"y": 0.57904296875
				},
				{
					"int_x": 648,
					"int_y": 741,
					"x": 0.6745989583333333,
					"y": 0.57904296875
				}
			],
			"rect": {
				"h": 0.03558593750000005,
				"int_h": 46,
				"int_w": 62,
				"int_x": 648,
				"int_y": 696,
				"w": 0.06392708333333341,
				"x": 0.6745989583333333,
				"y": 0.54345703125
			}
		},
		{
			"class_idx": 5,
			"name": "Kotex",
			"points": [
				{
					"int_x": 756,
					"int_y": 692,
					"x": 0.7875885416666666,
					"y": 0.54067578125
				},
				{
					"int_x": 829,
					"int_y": 692,
					"x": 0.864015625,
					"y": 0.54067578125
				},
				{
					"int_x": 829,
					"int_y": 750,
					"x": 0.864015625,
					"y": 0.58623046875
				},
				{
					"int_x": 756,
					"int_y": 750,
					"x": 0.7875885416666666,
					"y": 0.58623046875
				}
			],
			"rect": {
				"h": 0.04555468749999991,
				"int_h": 59,
				"int_w": 74,
				"int_x": 756,
				"int_y": 692,
				"w": 0.07642708333333337,
				"x": 0.7875885416666666,
				"y": 0.54067578125
			}
		},
		{
			"class_idx": 1,
			"name": "Bella",
			"points": [
				{
					"int_x": 242,
					"int_y": 721,
					"x": 0.252484375,
					"y": 0.5631210937500001
				},
				{
					"int_x": 321,
					"int_y": 721,
					"x": 0.33386979166666664,
					"y": 0.5631210937500001
				},
				{
					"int_x": 321,
					"int_y": 846,
					"x": 0.33386979166666664,
					"y": 0.66086328125
				},
				{
					"int_x": 242,
					"int_y": 846,
					"x": 0.252484375,
					"y": 0.66086328125
				}
			],
			"rect": {
				"h": 0.09774218749999997,
				"int_h": 126,
				"int_w": 80,
				"int_x": 242,
				"int_y": 721,
				"w": 0.08138541666666665,
				"x": 0.252484375,
				"y": 0.5631210937500001
			}
		},
		{
			"class_idx": 1,
			"name": "Bella",
			"points": [
				{
					"int_x": 317,
					"int_y": 722,
					"x": 0.32998958333333334,
					"y": 0.56371484375
				},
				{
					"int_x": 393,
					"int_y": 722,
					"x": 0.40909375,
					"y": 0.56371484375
				},
				{
					"int_x": 393,
					"int_y": 853,
					"x": 0.40909375,
					"y": 0.66647265625
				},
				{
					"int_x": 317,
					"int_y": 853,
					"x": 0.32998958333333334,
					"y": 0.66647265625
				}
			],
			"rect": {
				"h": 0.10275781249999993,
				"int_h": 132,
				"int_w": 77,
				"int_x": 317,
				"int_y": 722,
				"w": 0.07910416666666664,
				"x": 0.32998958333333334,
				"y": 0.56371484375
			}
		},
		{
			"class_idx": 1,
			"name": "Bella",
			"points": [
				{
					"int_x": 397,
					"int_y": 726,
					"x": 0.41341145833333337,
					"y": 0.5669179687500001
				},
				{
					"int_x": 473,
					"int_y": 726,
					"x": 0.49265104166666673,
					"y": 0.5669179687500001
				},
				{
					"int_x": 473,
					"int_y": 848,
					"x": 0.49265104166666673,
					"y": 0.66287890625
				},
				{
					"int_x": 397,
					"int_y": 848,
					"x": 0.41341145833333337,
					"y": 0.66287890625
				}
			],
			"rect": {
				"h": 0.0959609374999999,
				"int_h": 123,
				"int_w": 77,
				"int_x": 397,
				"int_y": 726,
				"w": 0.07923958333333336,
				"x": 0.41341145833333337,
				"y": 0.5669179687500001
			}
		},
		{
			"class_idx": 1,
			"name": "Bella",
			"points": [
				{
					"int_x": 474,
					"int_y": 719,
					"x": 0.4942083333333333,
					"y": 0.5616875
				},
				{
					"int_x": 553,
					"int_y": 719,
					"x": 0.5756875,
					"y": 0.5616875
				},
				{
					"int_x": 553,
					"int_y": 845,
					"x": 0.5756875,
					"y": 0.6599375
				},
				{
					"int_x": 474,
					"int_y": 845,
					"x": 0.4942083333333333,
					"y": 0.6599375
				}
			],
			"rect": {
				"h": 0.09824999999999995,
				"int_h": 127,
				"int_w": 80,
				"int_x": 474,
				"int_y": 719,
				"w": 0.08147916666666671,
				"x": 0.4942083333333333,
				"y": 0.5616875
			}
		},
		{
			"class_idx": 1,
			"name": "Bella",
			"points": [
				{
					"int_x": 553,
					"int_y": 726,
					"x": 0.5763802083333334,
					"y": 0.5668046875
				},
				{
					"int_x": 625,
					"int_y": 726,
					"x": 0.6508697916666668,
					"y": 0.5668046875
				},
				{
					"int_x": 625,
					"int_y": 852,
					"x": 0.6508697916666668,
					"y": 0.6659453125
				},
				{
					"int_x": 553,
					"int_y": 852,
					"x": 0.5763802083333334,
					"y": 0.6659453125
				}
			],
			"rect": {
				"h": 0.09914062499999998,
				"int_h": 127,
				"int_w": 73,
				"int_x": 553,
				"int_y": 726,
				"w": 0.07448958333333344,
				"x": 0.5763802083333334,
				"y": 0.5668046875
			}
		},
		{
			"class_idx": 5,
			"name": "Kotex",
			"points": [
				{
					"int_x": 640,
					"int_y": 736,
					"x": 0.6667760416666666,
					"y": 0.5748828125
				},
				{
					"int_x": 695,
					"int_y": 736,
					"x": 0.7239739583333333,
					"y": 0.5748828125
				},
				{
					"int_x": 695,
					"int_y": 803,
					"x": 0.7239739583333333,
					"y": 0.6271640625
				},
				{
					"int_x": 640,
					"int_y": 803,
					"x": 0.6667760416666666,
					"y": 0.6271640625
				}
			],
			"rect": {
				"h": 0.05228125000000006,
				"int_h": 68,
				"int_w": 56,
				"int_x": 640,
				"int_y": 736,
				"w": 0.05719791666666674,
				"x": 0.6667760416666666,
				"y": 0.5748828125
			}
		},
		{
			"class_idx": 5,
			"name": "Kotex",
			"points": [
				{
					"int_x": 698,
					"int_y": 750,
					"x": 0.7274479166666667,
					"y": 0.58625390625
				},
				{
					"int_x": 769,
					"int_y": 750,
					"x": 0.8011770833333334,
					"y": 0.58625390625
				},
				{
					"int_x": 769,
					"int_y": 812,
					"x": 0.8011770833333334,
					"y": 0.6346992187499999
				},
				{
					"int_x": 698,
					"int_y": 812,
					"x": 0.7274479166666667,
					"y": 0.6346992187499999
				}
			],
			"rect": {
				"h": 0.04844531249999995,
				"int_h": 63,
				"int_w": 72,
				"int_x": 698,
				"int_y": 750,
				"w": 0.07372916666666662,
				"x": 0.7274479166666667,
				"y": 0.58625390625
			}
		},
		{
			"class_idx": 5,
			"name": "Kotex",
			"points": [
				{
					"int_x": 771,
					"int_y": 750,
					"x": 0.8026770833333334,
					"y": 0.5863125
				},
				{
					"int_x": 842,
					"int_y": 750,
					"x": 0.8766354166666668,
					"y": 0.5863125
				},
				{
					"int_x": 842,
					"int_y": 810,
					"x": 0.8766354166666668,
					"y": 0.6328437499999999
				},
				{
					"int_x": 771,
					"int_y": 810,
					"x": 0.8026770833333334,
					"y": 0.6328437499999999
				}
			],
			"rect": {
				"h": 0.04653124999999991,
				"int_h": 61,
				"int_w": 72,
				"int_x": 771,
				"int_y": 750,
				"w": 0.07395833333333335,
				"x": 0.8026770833333334,
				"y": 0.5863125
			}
		},
		{
			"class_idx": 5,
			"name": "Kotex",
			"points": [
				{
					"int_x": 834,
					"int_y": 758,
					"x": 0.8692500000000001,
					"y": 0.59196875
				},
				{
					"int_x": 910,
					"int_y": 758,
					"x": 0.9483333333333335,
					"y": 0.59196875
				},
				{
					"int_x": 910,
					"int_y": 818,
					"x": 0.9483333333333335,
					"y": 0.639390625
				},
				{
					"int_x": 834,
					"int_y": 818,
					"x": 0.8692500000000001,
					"y": 0.639390625
				}
			],
			"rect": {
				"h": 0.04742187499999995,
				"int_h": 61,
				"int_w": 77,
				"int_x": 834,
				"int_y": 758,
				"w": 0.0790833333333334,
				"x": 0.8692500000000001,
				"y": 0.59196875
			}
		},
		{
			"class_idx": 5,
			"name": "Kotex",
			"points": [
				{
					"int_x": 832,
					"int_y": 694,
					"x": 0.8663749999999999,
					"y": 0.54217578125
				},
				{
					"int_x": 914,
					"int_y": 694,
					"x": 0.9521875,
					"y": 0.54217578125
				},
				{
					"int_x": 914,
					"int_y": 758,
					"x": 0.9521875,
					"y": 0.5924335937499999
				},
				{
					"int_x": 832,
					"int_y": 758,
					"x": 0.8663749999999999,
					"y": 0.5924335937499999
				}
			],
			"rect": {
				"h": 0.05025781249999994,
				"int_h": 65,
				"int_w": 83,
				"int_x": 832,
				"int_y": 694,
				"w": 0.08581250000000007,
				"x": 0.8663749999999999,
				"y": 0.54217578125
			}
		},
		{
			"class_idx": 5,
			"name": "Kotex",
			"points": [
				{
					"int_x": 912,
					"int_y": 760,
					"x": 0.949875,
					"y": 0.5937382812499999
				},
				{
					"int_x": 960,
					"int_y": 760,
					"x": 1.0,
					"y": 0.5937382812499999
				},
				{
					"int_x": 960,
					"int_y": 819,
					"x": 1.0,
					"y": 0.63969921875
				},
				{
					"int_x": 912,
					"int_y": 819,
					"x": 0.949875,
					"y": 0.63969921875
				}
			],
			"rect": {
				"h": 0.045960937500000076,
				"int_h": 60,
				"int_w": 48,
				"int_x": 912,
				"int_y": 760,
				"w": 0.050124999999999975,
				"x": 0.949875,
				"y": 0.5937382812499999
			}
		},
		{
			"class_idx": 5,
			"name": "Kotex",
			"points": [
				{
					"int_x": 918,
					"int_y": 696,
					"x": 0.9561458333333334,
					"y": 0.54357421875
				},
				{
					"int_x": 960,
					"int_y": 696,
					"x": 1.0,
					"y": 0.54357421875
				},
				{
					"int_x": 960,
					"int_y": 755,
					"x": 1.0,
					"y": 0.59001953125
				},
				{
					"int_x": 918,
					"int_y": 755,
					"x": 0.9561458333333334,
					"y": 0.59001953125
				}
			],
			"rect": {
				"h": 0.04644531249999995,
				"int_h": 60,
				"int_w": 42,
				"int_x": 918,
				"int_y": 696,
				"w": 0.04385416666666664,
				"x": 0.9561458333333334,
				"y": 0.54357421875
			}
		},
		{
			"class_idx": 5,
			"name": "Kotex",
			"points": [
				{
					"int_x": 637,
					"int_y": 801,
					"x": 0.6634322916666666,
					"y": 0.6258085937500001
				},
				{
					"int_x": 693,
					"int_y": 801,
					"x": 0.7222968750000001,
					"y": 0.6258085937500001
				},
				{
					"int_x": 693,
					"int_y": 879,
					"x": 0.7222968750000001,
					"y": 0.6866289062500001
				},
				{
					"int_x": 637,
					"int_y": 879,
					"x": 0.6634322916666666,
					"y": 0.6866289062500001
				}
			],
			"rect": {
				"h": 0.06082031249999997,
				"int_h": 79,
				"int_w": 57,
				"int_x": 637,
				"int_y": 801,
				"w": 0.05886458333333344,
				"x": 0.6634322916666666,
				"y": 0.6258085937500001
			}
		},
		{
			"class_idx": 5,
			"name": "Kotex",
			"points": [
				{
					"int_x": 697,
					"int_y": 848,
					"x": 0.725859375,
					"y": 0.6627265625
				},
				{
					"int_x": 760,
					"int_y": 848,
					"x": 0.7913489583333333,
					"y": 0.6627265625
				},
				{
					"int_x": 760,
					"int_y": 876,
					"x": 0.7913489583333333,
					"y": 0.6844609375
				},
				{
					"int_x": 697,
					"int_y": 876,
					"x": 0.725859375,
					"y": 0.6844609375
				}
			],
			"rect": {
				"h": 0.021734375000000083,
				"int_h": 29,
				"int_w": 64,
				"int_x": 697,
				"int_y": 848,
				"w": 0.06548958333333332,
				"x": 0.725859375,
				"y": 0.6627265625
			}
		},
		{
			"class_idx": 5,
			"name": "Kotex",
			"points": [
				{
					"int_x": 695,
					"int_y": 815,
					"x": 0.7236666666666667,
					"y": 0.6366210937500001
				},
				{
					"int_x": 762,
					"int_y": 815,
					"x": 0.7935625,
					"y": 0.6366210937500001
				},
				{
					"int_x": 762,
					"int_y": 849,
					"x": 0.7935625,
					"y": 0.66334765625
				},
				{
					"int_x": 695,
					"int_y": 849,
					"x": 0.7236666666666667,
					"y": 0.66334765625
				}
			],
			"rect": {
				"h": 0.02672656249999994,
				"int_h": 35,
				"int_w": 68,
				"int_x": 695,
				"int_y": 815,
				"w": 0.06989583333333327,
				"x": 0.7236666666666667,
				"y": 0.6366210937500001
			}
		},
		{
			"class_idx": 5,
			"name": "Kotex",
			"points": [
				{
					"int_x": 870,
					"int_y": 824,
					"x": 0.9064583333333334,
					"y": 0.6440273437499999
				},
				{
					"int_x": 960,
					"int_y": 824,
					"x": 1.0,
					"y": 0.6440273437499999
				},
				{
					"int_x": 960,
					"int_y": 893,
					"x": 1.0,
					"y": 0.69794140625
				},
				{
					"int_x": 870,
					"int_y": 893,
					"x": 0.9064583333333334,
					"y": 0.69794140625
				}
			],
			"rect": {
				"h": 0.05391406250000008,
				"int_h": 70,
				"int_w": 90,
				"int_x": 870,
				"int_y": 824,
				"w": 0.09354166666666663,
				"x": 0.9064583333333334,
				"y": 0.6440273437499999
			}
		},
		{
			"class_idx": 1,
			"name": "Bella",
			"points": [
				{
					"int_x": 254,
					"int_y": 847,
					"x": 0.26458333333333334,
					"y": 0.6620312500000001
				},
				{
					"int_x": 333,
					"int_y": 847,
					"x": 0.34708333333333335,
					"y": 0.6620312500000001
				},
				{
					"int_x": 333,
					"int_y": 991,
					"x": 0.34708333333333335,
					"y": 0.77390625
				},
				{
					"int_x": 254,
					"int_y": 991,
					"x": 0.26458333333333334,
					"y": 0.77390625
				}
			],
			"rect": {
				"h": 0.11187499999999995,
				"int_h": 145,
				"int_w": 80,
				"int_x": 254,
				"int_y": 847,
				"w": 0.08250000000000002,
				"x": 0.26458333333333334,
				"y": 0.6620312500000001
			}
		},
		{
			"class_idx": 5,
			"name": "Kotex",
			"points": [
				{
					"int_x": 643,
					"int_y": 883,
					"x": 0.6693697916666665,
					"y": 0.6895273437499999
				},
				{
					"int_x": 699,
					"int_y": 883,
					"x": 0.7276302083333333,
					"y": 0.6895273437499999
				},
				{
					"int_x": 699,
					"int_y": 945,
					"x": 0.7276302083333333,
					"y": 0.7380820312499999
				},
				{
					"int_x": 643,
					"int_y": 945,
					"x": 0.6693697916666665,
					"y": 0.7380820312499999
				}
			],
			"rect": {
				"h": 0.04855468750000003,
				"int_h": 63,
				"int_w": 57,
				"int_x": 643,
				"int_y": 883,
				"w": 0.0582604166666667,
				"x": 0.6693697916666665,
				"y": 0.6895273437499999
			}
		},
		{
			"class_idx": 5,
			"name": "Kotex",
			"points": [
				{
					"int_x": 696,
					"int_y": 888,
					"x": 0.7251249999999999,
					"y": 0.6934570312499999
				},
				{
					"int_x": 784,
					"int_y": 888,
					"x": 0.8168958333333333,
					"y": 0.6934570312499999
				},
				{
					"int_x": 784,
					"int_y": 962,
					"x": 0.8168958333333333,
					"y": 0.7513554687499999
				},
				{
					"int_x": 696,
					"int_y": 962,
					"x": 0.7251249999999999,
					"y": 0.7513554687499999
				}
			],
			"rect": {
				"h": 0.05789843750000001,
				"int_h": 75,
				"int_w": 89,
				"int_x": 696,
				"int_y": 888,
				"w": 0.09177083333333336,
				"x": 0.7251249999999999,
				"y": 0.6934570312499999
			}
		},
		{
			"class_idx": 5,
			"name": "Kotex",
			"points": [
				{
					"int_x": 787,
					"int_y": 836,
					"x": 0.8195572916666666,
					"y": 0.65341015625
				},
				{
					"int_x": 873,
					"int_y": 836,
					"x": 0.9088802083333333,
					"y": 0.65341015625
				},
				{
					"int_x": 873,
					"int_y": 970,
					"x": 0.9088802083333333,
					"y": 0.75818359375
				},
				{
					"int_x": 787,
					"int_y": 970,
					"x": 0.8195572916666666,
					"y": 0.75818359375
				}
			],
			"rect": {
				"h": 0.10477343750000001,
				"int_h": 135,
				"int_w": 87,
				"int_x": 787,
				"int_y": 836,
				"w": 0.0893229166666667,
				"x": 0.8195572916666666,
				"y": 0.65341015625
			}
		},
		{
			"class_idx": 5,
			"name": "Kotex",
			"points": [
				{
					"int_x": 869,
					"int_y": 892,
					"x": 0.9052916666666666,
					"y": 0.6972265625
				},
				{
					"int_x": 960,
					"int_y": 892,
					"x": 1.0,
					"y": 0.6972265625
				},
				{
					"int_x": 960,
					"int_y": 960,
					"x": 1.0,
					"y": 0.7499921875
				},
				{
					"int_x": 869,
					"int_y": 960,
					"x": 0.9052916666666666,
					"y": 0.7499921875
				}
			],
			"rect": {
				"h": 0.05276562499999993,
				"int_h": 69,
				"int_w": 91,
				"int_x": 869,
				"int_y": 892,
				"w": 0.0947083333333334,
				"x": 0.9052916666666666,
				"y": 0.6972265625
			}
		},
		{
			"class_idx": 7,
			"name": "Other",
			"points": [
				{
					"int_x": 265,
					"int_y": 1020,
					"x": 0.2764947916666667,
					"y": 0.79676171875
				},
				{
					"int_x": 341,
					"int_y": 1020,
					"x": 0.35567187499999997,
					"y": 0.79676171875
				},
				{
					"int_x": 341,
					"int_y": 1062,
					"x": 0.35567187499999997,
					"y": 0.8299414062499999
				},
				{
					"int_x": 265,
					"int_y": 1062,
					"x": 0.2764947916666667,
					"y": 0.8299414062499999
				}
			],
			"rect": {
				"h": 0.03317968749999989,
				"int_h": 43,
				"int_w": 77,
				"int_x": 265,
				"int_y": 1020,
				"w": 0.07917708333333329,
				"x": 0.2764947916666667,
				"y": 0.79676171875
			}
		},
		{
			"class_idx": 7,
			"name": "Other",
			"points": [
				{
					"int_x": 344,
					"int_y": 1028,
					"x": 0.35832812499999994,
					"y": 0.802921875
				},
				{
					"int_x": 420,
					"int_y": 1028,
					"x": 0.437671875,
					"y": 0.802921875
				},
				{
					"int_x": 420,
					"int_y": 1067,
					"x": 0.437671875,
					"y": 0.8337656250000001
				},
				{
					"int_x": 344,
					"int_y": 1067,
					"x": 0.35832812499999994,
					"y": 0.8337656250000001
				}
			],
			"rect": {
				"h": 0.03084375000000006,
				"int_h": 40,
				"int_w": 77,
				"int_x": 344,
				"int_y": 1028,
				"w": 0.07934375000000005,
				"x": 0.35832812499999994,
				"y": 0.802921875
			}
		},
		{
			"class_idx": 7,
			"name": "Other",
			"points": [
				{
					"int_x": 427,
					"int_y": 1041,
					"x": 0.44471354166666666,
					"y": 0.81362890625
				},
				{
					"int_x": 515,
					"int_y": 1041,
					"x": 0.536265625,
					"y": 0.81362890625
				},
				{
					"int_x": 515,
					"int_y": 1075,
					"x": 0.536265625,
					"y": 0.83987109375
				},
				{
					"int_x": 427,
					"int_y": 1075,
					"x": 0.44471354166666666,
					"y": 0.83987109375
				}
			],
			"rect": {
				"h": 0.02624218750000007,
				"int_h": 35,
				"int_w": 89,
				"int_x": 427,
				"int_y": 1041,
				"w": 0.09155208333333331,
				"x": 0.44471354166666666,
				"y": 0.81362890625
			}
		},
		{
			"class_idx": 5,
			"name": "Kotex",
			"points": [
				{
					"int_x": 638,
					"int_y": 945,
					"x": 0.6647760416666666,
					"y": 0.7382421874999999
				},
				{
					"int_x": 710,
					"int_y": 945,
					"x": 0.7394322916666667,
					"y": 0.7382421874999999
				},
				{
					"int_x": 710,
					"int_y": 1077,
					"x": 0.7394322916666667,
					"y": 0.8413046875
				},
				{
					"int_x": 638,
					"int_y": 1077,
					"x": 0.6647760416666666,
					"y": 0.8413046875
				}
			],
			"rect": {
				"h": 0.10306250000000006,
				"int_h": 133,
				"int_w": 73,
				"int_x": 638,
				"int_y": 945,
				"w": 0.07465625000000009,
				"x": 0.6647760416666666,
				"y": 0.7382421874999999
			}
		},
		{
			"class_idx": 5,
			"name": "Kotex",
			"points": [
				{
					"int_x": 705,
					"int_y": 969,
					"x": 0.7343020833333334,
					"y": 0.757140625
				},
				{
					"int_x": 791,
					"int_y": 969,
					"x": 0.8236979166666667,
					"y": 0.757140625
				},
				{
					"int_x": 791,
					"int_y": 1098,
					"x": 0.8236979166666667,
					"y": 0.857546875
				},
				{
					"int_x": 705,
					"int_y": 1098,
					"x": 0.7343020833333334,
					"y": 0.857546875
				}
			],
			"rect": {
				"h": 0.10040625000000003,
				"int_h": 130,
				"int_w": 87,
				"int_x": 705,
				"int_y": 969,
				"w": 0.08939583333333334,
				"x": 0.7343020833333334,
				"y": 0.757140625
			}
		},
		{
			"class_idx": 5,
			"name": "Kotex",
			"points": [
				{
					"int_x": 790,
					"int_y": 973,
					"x": 0.8226197916666667,
					"y": 0.76048828125
				},
				{
					"int_x": 871,
					"int_y": 973,
					"x": 0.9077968750000001,
					"y": 0.76048828125
				},
				{
					"int_x": 871,
					"int_y": 1096,
					"x": 0.9077968750000001,
					"y": 0.8564960937499999
				},
				{
					"int_x": 790,
					"int_y": 1096,
					"x": 0.8226197916666667,
					"y": 0.8564960937499999
				}
			],
			"rect": {
				"h": 0.0960078124999999,
				"int_h": 124,
				"int_w": 82,
				"int_x": 790,
				"int_y": 973,
				"w": 0.0851770833333334,
				"x": 0.8226197916666667,
				"y": 0.76048828125
			}
		},
		{
			"class_idx": 5,
			"name": "Kotex",
			"points": [
				{
					"int_x": 867,
					"int_y": 972,
					"x": 0.9027239583333333,
					"y": 0.75914453125
				},
				{
					"int_x": 937,
					"int_y": 972,
					"x": 0.9764843750000001,
					"y": 0.75914453125
				},
				{
					"int_x": 937,
					"int_y": 1100,
					"x": 0.9764843750000001,
					"y": 0.85952734375
				},
				{
					"int_x": 867,
					"int_y": 1100,
					"x": 0.9027239583333333,
					"y": 0.85952734375
				}
			],
			"rect": {
				"h": 0.10038281249999992,
				"int_h": 129,
				"int_w": 71,
				"int_x": 867,
				"int_y": 972,
				"w": 0.07376041666666677,
				"x": 0.9027239583333333,
				"y": 0.75914453125
			}
		},
		{
			"class_idx": 5,
			"name": "Kotex",
			"points": [
				{
					"int_x": 938,
					"int_y": 973,
					"x": 0.9765885416666666,
					"y": 0.76038671875
				},
				{
					"int_x": 960,
					"int_y": 973,
					"x": 0.9999947916666667,
					"y": 0.76038671875
				},
				{
					"int_x": 960,
					"int_y": 1108,
					"x": 0.9999947916666667,
					"y": 0.86586328125
				},
				{
					"int_x": 938,
					"int_y": 1108,
					"x": 0.9765885416666666,
					"y": 0.86586328125
				}
			],
			"rect": {
				"h": 0.10547656250000004,
				"int_h": 136,
				"int_w": 22,
				"int_x": 938,
				"int_y": 973,
				"w": 0.023406250000000073,
				"x": 0.9765885416666666,
				"y": 0.76038671875
			}
		},
		{
			"class_idx": 7,
			"name": "Other",
			"points": [
				{
					"int_x": 253,
					"int_y": 1067,
					"x": 0.26319270833333336,
					"y": 0.83332421875
				},
				{
					"int_x": 347,
					"int_y": 1067,
					"x": 0.36136979166666666,
					"y": 0.83332421875
				},
				{
					"int_x": 347,
					"int_y": 1118,
					"x": 0.36136979166666666,
					"y": 0.87323828125
				},
				{
					"int_x": 253,
					"int_y": 1118,
					"x": 0.26319270833333336,
					"y": 0.87323828125
				}
			],
			"rect": {
				"h": 0.03991406250000007,
				"int_h": 52,
				"int_w": 95,
				"int_x": 253,
				"int_y": 1067,
				"w": 0.0981770833333333,
				"x": 0.26319270833333336,
				"y": 0.83332421875
			}
		},
		{
			"class_idx": 7,
			"name": "Other",
			"points": [
				{
					"int_x": 345,
					"int_y": 1061,
					"x": 0.3598854166666667,
					"y": 0.829140625
				},
				{
					"int_x": 431,
					"int_y": 1061,
					"x": 0.4489479166666667,
					"y": 0.829140625
				},
				{
					"int_x": 431,
					"int_y": 1094,
					"x": 0.4489479166666667,
					"y": 0.8546093749999999
				},
				{
					"int_x": 345,
					"int_y": 1094,
					"x": 0.3598854166666667,
					"y": 0.8546093749999999
				}
			],
			"rect": {
				"h": 0.02546874999999993,
				"int_h": 34,
				"int_w": 87,
				"int_x": 345,
				"int_y": 1061,
				"w": 0.08906250000000004,
				"x": 0.3598854166666667,
				"y": 0.829140625
			}
		},
		{
			"class_idx": 7,
			"name": "Other",
			"points": [
				{
					"int_x": 430,
					"int_y": 1078,
					"x": 0.44796874999999997,
					"y": 0.8419257812500001
				},
				{
					"int_x": 518,
					"int_y": 1078,
					"x": 0.5391770833333334,
					"y": 0.8419257812500001
				},
				{
					"int_x": 518,
					"int_y": 1108,
					"x": 0.5391770833333334,
					"y": 0.86552734375
				},
				{
					"int_x": 430,
					"int_y": 1108,
					"x": 0.44796874999999997,
					"y": 0.86552734375
				}
			],
			"rect": {
				"h": 0.023601562499999895,
				"int_h": 31,
				"int_w": 89,
				"int_x": 430,
				"int_y": 1078,
				"w": 0.09120833333333339,
				"x": 0.44796874999999997,
				"y": 0.8419257812500001
			}
		},
		{
			"class_idx": 5,
			"name": "Kotex",
			"points": [
				{
					"int_x": 644,
					"int_y": 1075,
					"x": 0.6704791666666667,
					"y": 0.8398867187500001
				},
				{
					"int_x": 701,
					"int_y": 1075,
					"x": 0.7305416666666666,
					"y": 0.8398867187500001
				},
				{
					"int_x": 701,
					"int_y": 1100,
					"x": 0.7305416666666666,
					"y": 0.8591914062500001
				},
				{
					"int_x": 644,
					"int_y": 1100,
					"x": 0.6704791666666667,
					"y": 0.8591914062500001
				}
			],
			"rect": {
				"h": 0.01930468750000003,
				"int_h": 26,
				"int_w": 58,
				"int_x": 644,
				"int_y": 1075,
				"w": 0.06006249999999991,
				"x": 0.6704791666666667,
				"y": 0.8398867187500001
			}
		},
		{
			"class_idx": 0,
			"name": "Always",
			"points": [
				{
					"int_x": 292,
					"int_y": 1117,
					"x": 0.30368229166666666,
					"y": 0.8730117187499999
				},
				{
					"int_x": 363,
					"int_y": 1117,
					"x": 0.3782552083333333,
					"y": 0.8730117187499999
				},
				{
					"int_x": 363,
					"int_y": 1222,
					"x": 0.3782552083333333,
					"y": 0.95445703125
				},
				{
					"int_x": 292,
					"int_y": 1222,
					"x": 0.30368229166666666,
					"y": 0.95445703125
				}
			],
			"rect": {
				"h": 0.08144531250000009,
				"int_h": 106,
				"int_w": 72,
				"int_x": 292,
				"int_y": 1117,
				"w": 0.07457291666666666,
				"x": 0.30368229166666666,
				"y": 0.8730117187499999
			}
		},
		{
			"class_idx": 0,
			"name": "Always",
			"points": [
				{
					"int_x": 346,
					"int_y": 1151,
					"x": 0.36018229166666665,
					"y": 0.8988828124999999
				},
				{
					"int_x": 419,
					"int_y": 1151,
					"x": 0.43658854166666666,
					"y": 0.8988828124999999
				},
				{
					"int_x": 419,
					"int_y": 1237,
					"x": 0.43658854166666666,
					"y": 0.9665078125
				},
				{
					"int_x": 346,
					"int_y": 1237,
					"x": 0.36018229166666665,
					"y": 0.9665078125
				}
			],
			"rect": {
				"h": 0.06762500000000005,
				"int_h": 87,
				"int_w": 74,
				"int_x": 346,
				"int_y": 1151,
				"w": 0.07640625000000001,
				"x": 0.36018229166666665,
				"y": 0.8988828124999999
			}
		},
		{
			"class_idx": 0,
			"name": "Always",
			"points": [
				{
					"int_x": 493,
					"int_y": 1124,
					"x": 0.51303125,
					"y": 0.8781523437500001
				},
				{
					"int_x": 566,
					"int_y": 1124,
					"x": 0.5893020833333333,
					"y": 0.8781523437500001
				},
				{
					"int_x": 566,
					"int_y": 1275,
					"x": 0.5893020833333333,
					"y": 0.9959101562500001
				},
				{
					"int_x": 493,
					"int_y": 1275,
					"x": 0.51303125,
					"y": 0.9959101562500001
				}
			],
			"rect": {
				"h": 0.11775781250000006,
				"int_h": 152,
				"int_w": 74,
				"int_x": 493,
				"int_y": 1124,
				"w": 0.07627083333333329,
				"x": 0.51303125,
				"y": 0.8781523437500001
			}
		},
		{
			"class_idx": 5,
			"name": "Kotex",
			"points": [
				{
					"int_x": 640,
					"int_y": 1100,
					"x": 0.6662083333333333,
					"y": 0.8593710937500001
				},
				{
					"int_x": 718,
					"int_y": 1100,
					"x": 0.7474375,
					"y": 0.8593710937500001
				},
				{
					"int_x": 718,
					"int_y": 1246,
					"x": 0.7474375,
					"y": 0.97366015625
				},
				{
					"int_x": 640,
					"int_y": 1246,
					"x": 0.6662083333333333,
					"y": 0.97366015625
				}
			],
			"rect": {
				"h": 0.11428906249999993,
				"int_h": 147,
				"int_w": 79,
				"int_x": 640,
				"int_y": 1100,
				"w": 0.08122916666666669,
				"x": 0.6662083333333333,
				"y": 0.8593710937500001
			}
		},
		{
			"class_idx": 5,
			"name": "Kotex",
			"points": [
				{
					"int_x": 790,
					"int_y": 1123,
					"x": 0.8231041666666666,
					"y": 0.87754296875
				},
				{
					"int_x": 857,
					"int_y": 1123,
					"x": 0.8930625,
					"y": 0.87754296875
				},
				{
					"int_x": 857,
					"int_y": 1244,
					"x": 0.8930625,
					"y": 0.97198828125
				},
				{
					"int_x": 790,
					"int_y": 1244,
					"x": 0.8231041666666666,
					"y": 0.97198828125
				}
			],
			"rect": {
				"h": 0.09444531249999999,
				"int_h": 122,
				"int_w": 68,
				"int_x": 790,
				"int_y": 1123,
				"w": 0.06995833333333334,
				"x": 0.8231041666666666,
				"y": 0.87754296875
			}
		},
		{
			"class_idx": 5,
			"name": "Kotex",
			"points": [
				{
					"int_x": 848,
					"int_y": 1135,
					"x": 0.8837291666666668,
					"y": 0.88644921875
				},
				{
					"int_x": 932,
					"int_y": 1135,
					"x": 0.9703333333333334,
					"y": 0.88644921875
				},
				{
					"int_x": 932,
					"int_y": 1214,
					"x": 0.9703333333333334,
					"y": 0.94856640625
				},
				{
					"int_x": 848,
					"int_y": 1214,
					"x": 0.8837291666666668,
					"y": 0.94856640625
				}
			],
			"rect": {
				"h": 0.06211718749999995,
				"int_h": 80,
				"int_w": 85,
				"int_x": 848,
				"int_y": 1135,
				"w": 0.0866041666666666,
				"x": 0.8837291666666668,
				"y": 0.88644921875
			}
		},
		{
			"class_idx": 5,
			"name": "Kotex",
			"points": [
				{
					"int_x": 854,
					"int_y": 1206,
					"x": 0.8892083333333334,
					"y": 0.9425585937500001
				},
				{
					"int_x": 931,
					"int_y": 1206,
					"x": 0.9696666666666667,
					"y": 0.9425585937500001
				},
				{
					"int_x": 931,
					"int_y": 1254,
					"x": 0.9696666666666667,
					"y": 0.97956640625
				},
				{
					"int_x": 854,
					"int_y": 1254,
					"x": 0.8892083333333334,
					"y": 0.97956640625
				}
			],
			"rect": {
				"h": 0.03700781249999996,
				"int_h": 49,
				"int_w": 78,
				"int_x": 854,
				"int_y": 1206,
				"w": 0.0804583333333333,
				"x": 0.8892083333333334,
				"y": 0.9425585937500001
			}
		},
		{
			"class_idx": 5,
			"name": "Kotex",
			"points": [
				{
					"int_x": 928,
					"int_y": 1125,
					"x": 0.9670208333333333,
					"y": 0.879
				},
				{
					"int_x": 960,
					"int_y": 1125,
					"x": 0.9999999999999999,
					"y": 0.879
				},
				{
					"int_x": 960,
					"int_y": 1249,
					"x": 0.9999999999999999,
					"y": 0.976140625
				},
				{
					"int_x": 928,
					"int_y": 1249,
					"x": 0.9670208333333333,
					"y": 0.976140625
				}
			],
			"rect": {
				"h": 0.09714062499999998,
				"int_h": 125,
				"int_w": 32,
				"int_x": 928,
				"int_y": 1125,
				"w": 0.03297916666666656,
				"x": 0.9670208333333333,
				"y": 0.879
			}
		},
		{
			"class_idx": 0,
			"name": "Always",
			"points": [
				{
					"int_x": 229,
					"int_y": 1197,
					"x": 0.23805729166666667,
					"y": 0.93547265625
				},
				{
					"int_x": 291,
					"int_y": 1197,
					"x": 0.30338020833333335,
					"y": 0.93547265625
				},
				{
					"int_x": 291,
					"int_y": 1280,
					"x": 0.30338020833333335,
					"y": 0.9999960937500001
				},
				{
					"int_x": 229,
					"int_y": 1280,
					"x": 0.23805729166666667,
					"y": 0.9999960937500001
				}
			],
			"rect": {
				"h": 0.06452343750000011,
				"int_h": 83,
				"int_w": 63,
				"int_x": 229,
				"int_y": 1197,
				"w": 0.06532291666666667,
				"x": 0.23805729166666667,
				"y": 0.93547265625
			}
		},
		{
			"class_idx": 0,
			"name": "Always",
			"points": [
				{
					"int_x": 294,
					"int_y": 1223,
					"x": 0.3058489583333333,
					"y": 0.9556757812500001
				},
				{
					"int_x": 347,
					"int_y": 1223,
					"x": 0.36138020833333334,
					"y": 0.9556757812500001
				},
				{
					"int_x": 347,
					"int_y": 1274,
					"x": 0.36138020833333334,
					"y": 0.99569921875
				},
				{
					"int_x": 294,
					"int_y": 1274,
					"x": 0.3058489583333333,
					"y": 0.99569921875
				}
			],
			"rect": {
				"h": 0.040023437499999925,
				"int_h": 52,
				"int_w": 54,
				"int_x": 294,
				"int_y": 1223,
				"w": 0.05553125000000003,
				"x": 0.3058489583333333,
				"y": 0.9556757812500001
			}
		},
		{
			"class_idx": 0,
			"name": "Always",
			"points": [
				{
					"int_x": 427,
					"int_y": 1231,
					"x": 0.4448958333333334,
					"y": 0.9614062499999999
				},
				{
					"int_x": 496,
					"int_y": 1231,
					"x": 0.5163541666666667,
					"y": 0.9614062499999999
				},
				{
					"int_x": 496,
					"int_y": 1271,
					"x": 0.5163541666666667,
					"y": 0.99328125
				},
				{
					"int_x": 427,
					"int_y": 1271,
					"x": 0.4448958333333334,
					"y": 0.99328125
				}
			],
			"rect": {
				"h": 0.0318750000000001,
				"int_h": 41,
				"int_w": 70,
				"int_x": 427,
				"int_y": 1231,
				"w": 0.07145833333333329,
				"x": 0.4448958333333334,
				"y": 0.9614062499999999
			}
		},
		{
			"class_idx": 5,
			"name": "Kotex",
			"points": [
				{
					"int_x": 644,
					"int_y": 1250,
					"x": 0.6706927083333333,
					"y": 0.9762187499999999
				},
				{
					"int_x": 721,
					"int_y": 1250,
					"x": 0.7509739583333334,
					"y": 0.9762187499999999
				},
				{
					"int_x": 721,
					"int_y": 1280,
					"x": 0.7509739583333334,
					"y": 1.0
				},
				{
					"int_x": 644,
					"int_y": 1280,
					"x": 0.6706927083333333,
					"y": 1.0
				}
			],
			"rect": {
				"h": 0.023781250000000087,
				"int_h": 30,
				"int_w": 78,
				"int_x": 644,
				"int_y": 1250,
				"w": 0.08028125000000008,
				"x": 0.6706927083333333,
				"y": 0.9762187499999999
			}
		},
		{
			"class_idx": 5,
			"name": "Kotex",
			"points": [
				{
					"int_x": 785,
					"int_y": 1250,
					"x": 0.8180833333333334,
					"y": 0.97647265625
				},
				{
					"int_x": 848,
					"int_y": 1250,
					"x": 0.8834583333333333,
					"y": 0.97647265625
				},
				{
					"int_x": 848,
					"int_y": 1280,
					"x": 0.8834583333333333,
					"y": 0.99999609375
				},
				{
					"int_x": 785,
					"int_y": 1280,
					"x": 0.8180833333333334,
					"y": 0.99999609375
				}
			],
			"rect": {
				"h": 0.023523437499999966,
				"int_h": 30,
				"int_w": 64,
				"int_x": 785,
				"int_y": 1250,
				"w": 0.06537499999999996,
				"x": 0.8180833333333334,
				"y": 0.97647265625
			}
		},
		{
			"class_idx": 5,
			"name": "Kotex",
			"points": [
				{
					"int_x": 847,
					"int_y": 1253,
					"x": 0.8823177083333333,
					"y": 0.97881640625
				},
				{
					"int_x": 935,
					"int_y": 1253,
					"x": 0.973953125,
					"y": 0.97881640625
				},
				{
					"int_x": 935,
					"int_y": 1280,
					"x": 0.973953125,
					"y": 0.9999960937500001
				},
				{
					"int_x": 847,
					"int_y": 1280,
					"x": 0.8823177083333333,
					"y": 0.9999960937500001
				}
			],
			"rect": {
				"h": 0.0211796875000001,
				"int_h": 27,
				"int_w": 89,
				"int_x": 847,
				"int_y": 1253,
				"w": 0.09163541666666664,
				"x": 0.8823177083333333,
				"y": 0.97881640625
			}
		},
		{
			"class_idx": 3,
			"name": "Bella tampo",
			"points": [
				{
					"int_x": 516,
					"int_y": 1082,
					"x": 0.5374087591240876,
					"y": 0.8454172366621067
				},
				{
					"int_x": 591,
					"int_y": 1082,
					"x": 0.615875912408759,
					"y": 0.8454172366621067
				},
				{
					"int_x": 591,
					"int_y": 1121,
					"x": 0.615875912408759,
					"y": 0.8755129958960328
				},
				{
					"int_x": 516,
					"int_y": 1121,
					"x": 0.5374087591240876,
					"y": 0.8755129958960328
				}
			],
			"rect": {
				"h": 0.030095759233926156,
				"int_h": 40,
				"int_w": 76,
				"int_x": 516,
				"int_y": 1082,
				"w": 0.07846715328467146,
				"x": 0.5374087591240876,
				"y": 0.8454172366621067
			}
		}
	],
	"timestamp": 1743415348,
	"version": "1.10.18-1"
}
